ld/__init__.py
ld/android/LDFramework.py
ld/android/__init__.py
ld/android/action/Actions.py
ld/android/element/Color.py
ld/android/element/Image.py
ld/android/element/Node.py
ld/android/element/Ocr.py
ld/android/environment/Device.py
ld/android/environment/Intent.py
ld/common/CommonClass.py
ld/common/ListUtil.py
ld/common/Logger.py
ld/common/StrUtil.py
ld/common/TimeUtil.py
ld/common/TypeUtil.py
ld_as_framework-1.1.9.dist-info/LICENSE
ld_as_framework-1.1.9.dist-info/METADATA
ld_as_framework-1.1.9.dist-info/WHEEL
ld_as_framework-1.1.9.dist-info/top_level.txt
ld_as_framework-1.1.9.dist-info/RECORD
