Metadata-Version: 2.1
Name: ld-as-framework
Version: 1.1.9
Summary: 零动AS插件提示包
Author-email: 零动学院 <1132454419@qq.com>
Project-URL: Homepage, https://www.yuque.com/xianle-skqwj/ld
Classifier: Programming Language :: Python :: 3
Classifier: License :: OSI Approved :: MIT License
Classifier: Operating System :: OS Independent
Requires-Python: >=3.8
License-File: LICENSE
Requires-Dist: ascript-tip
